albucore/__init__.py
albucore/decorators.py
albucore/functions.py
albucore/utils.py
albucore-0.0.34.dist-info/licenses/LICENSE
albucore-0.0.34.dist-info/METADATA
albucore-0.0.34.dist-info/WHEEL
albucore-0.0.34.dist-info/top_level.txt
albucore-0.0.34.dist-info/RECORD
