Metadata-Version: 2.4
Name: albucore
Version: 0.0.34
Summary: High-performance image processing functions for deep learning and computer vision.
Author: Vladimir Iglovikov
Maintainer: Vladimir Iglovikov
License: MIT License
Keywords: deep learning,image processing
Classifier: Development Status :: 5 - Production/Stable
Classifier: Intended Audience :: Developers
Classifier: Intended Audience :: Science/Research
Classifier: License :: OSI Approved :: MIT License
Classifier: Operating System :: OS Independent
Classifier: Programming Language :: Python
Classifier: Programming Language :: Python :: 3 :: Only
Classifier: Programming Language :: Python :: 3.10
Classifier: Programming Language :: Python :: 3.11
Classifier: Programming Language :: Python :: 3.12
Classifier: Programming Language :: Python :: 3.13
Classifier: Programming Language :: Python :: 3.14
Classifier: Topic :: Scientific/Engineering :: Artificial Intelligence
Classifier: Topic :: Scientific/Engineering :: Image Processing
Classifier: Topic :: Software Development :: Libraries
Classifier: Topic :: Software Development :: Libraries :: Python Modules
Classifier: Typing :: Typed
Requires-Python: >=3.10
License-File: LICENSE
Requires-Dist: numpy>=1.24.4
Requires-Dist: stringzilla>=3.10.4
Requires-Dist: simsimd>=5.9.2
Requires-Dist: opencv-python-headless>=4.9.0.80
Dynamic: license-file
Dynamic: requires-dist
